netshare/__init__.py
netshare/__main__.py
netshare/app.py
netshare/config.py
netshare/templates/browse.html
netshare/templates/error.html
netshare/templates/index.html
netshare-1.0.4.dist-info/licenses/LICENSE
netshare-1.0.4.dist-info/METADATA
netshare-1.0.4.dist-info/WHEEL
netshare-1.0.4.dist-info/entry_points.txt
netshare-1.0.4.dist-info/top_level.txt
netshare-1.0.4.dist-info/RECORD
