Metadata-Version: 2.4
Name: netshare
Version: 1.0.4
Summary: Secure network file sharing tool for local WiFi networks
Author: NetShare Contributors
License: GPL-3.0
Project-URL: Homepage, https://github.com/yourusername/netshare
Project-URL: Issues, https://github.com/yourusername/netshare/issues
Project-URL: Repository, https://github.com/yourusername/netshare
Keywords: file-sharing,network,wifi,android,flask,qr-code,local-network,file-transfer
Classifier: Development Status :: 4 - Beta
Classifier: Intended Audience :: End Users/Desktop
Classifier: Intended Audience :: Developers
Classifier: Topic :: Communications :: File Sharing
Classifier: Topic :: Internet :: WWW/HTTP :: HTTP Servers
Classifier: License :: OSI Approved :: GNU General Public License v3 (GPLv3)
Classifier: Programming Language :: Python :: 3
Classifier: Programming Language :: Python :: 3.7
Classifier: Programming Language :: Python :: 3.8
Classifier: Programming Language :: Python :: 3.9
Classifier: Programming Language :: Python :: 3.10
Classifier: Programming Language :: Python :: 3.11
Classifier: Programming Language :: Python :: 3.12
Classifier: Operating System :: OS Independent
Classifier: Operating System :: Microsoft :: Windows
Classifier: Operating System :: POSIX :: Linux
Classifier: Operating System :: MacOS
Classifier: Environment :: Console
Classifier: Environment :: Web Environment
Requires-Python: >=3.7
License-File: LICENSE
Requires-Dist: Flask>=3.0.0
Requires-Dist: qrcode>=7.4.2
Requires-Dist: Pillow>=9.0.0
Provides-Extra: dev
Requires-Dist: build>=0.10.0; extra == "dev"
Requires-Dist: twine>=4.0.0; extra == "dev"
Dynamic: license-file
